{
  "c51_tipo_factura": [
    {
      "cod_tipo_factura": "101",
      "desc_tipo_factura": "Venta lnterna "
    },
    {
      "cod_tipo_factura": "102",
      "desc_tipo_factura": "Exportación "
    },
    {
      "cod_tipo_factura": "103",
      "desc_tipo_factura": "No Domiciliados "
    },
    {
      "cod_tipo_factura": "104",
      "desc_tipo_factura": "Venta Interna %u2013 Anticipos "
    },
    {
      "cod_tipo_factura": "105",
      "desc_tipo_factura": "Venta Itinerante "
    },
    {
      "cod_tipo_factura": "106",
      "desc_tipo_factura": "Factura Guía "
    },
    {
      "cod_tipo_factura": "107",
      "desc_tipo_factura": "Venta Arroz Pilado "
    },
    {
      "cod_tipo_factura": "108",
      "desc_tipo_factura": "Factura - Comprobante de Percepción "
    },
    {
      "cod_tipo_factura": "110",
      "desc_tipo_factura": "Factura - Guía remitente "
    },
    {
      "cod_tipo_factura": "111",
      "desc_tipo_factura": "Factura - Guía transportista "
    }
  ]
}